<?xml version="1.0"?><contentRecord xmlns="http://ns.adobe.com/digitalpublishing"><dp:addDate xmlns:dp="http://ns.adobe.com/digitalpublishing">2020-09-03T14:59:49Z</dp:addDate><dp:content xmlns:dp="http://ns.adobe.com/digitalpublishing" href="file:///C:/Users/Public/Videos/New%20folder/Mega%20Nursing/Epidemiology%20%26%20Statistics/(Statistics%20for%20Biology%20and%20Health)%20Klaus%20Krickeberg,%20Van%20Trong%20Pham,%20Thi%20My%20Hanh%20Pham-Epidemiology_%20Key%20to%20Prevention%20(Statisti.pdf"></dp:content><dp:metadata xmlns:dp="http://ns.adobe.com/digitalpublishing"><dc:title xmlns:dc="http://purl.org/dc/elements/1.1/">Epidemiology_ Key to Prevention</dc:title><dc:creator xmlns:dc="http://purl.org/dc/elements/1.1/">Klaus Krickeberg, Van Trong Pham, Thi My Hanh Pham</dc:creator></dp:metadata><dp:privateData xmlns:dp="http://ns.adobe.com/digitalpublishing"><totalPageCount xmlns="http://ns.adobe.com/digitaleditions">272</totalPageCount></dp:privateData><dp:tags xmlns:dp="http://ns.adobe.com/digitalpublishing"><dp:tag>private:ub9</dp:tag></dp:tags></contentRecord>