<?xml version="1.0"?><contentRecord xmlns="http://ns.adobe.com/digitalpublishing"><dp:addDate xmlns:dp="http://ns.adobe.com/digitalpublishing">2020-09-03T15:24:54Z</dp:addDate><dp:content xmlns:dp="http://ns.adobe.com/digitalpublishing" href="file:///C:/Users/Public/Videos/New%20folder/NVX/Deveraux,%20Jude%20-%20[Edilean%203]%20-%20Scarlet%20Nights%20(2010,%20Simon%20and%20Schuster,%209781439107973).epub"></dp:content><dp:metadata xmlns:dp="http://ns.adobe.com/digitalpublishing"><dc:identifier xmlns:dc="http://purl.org/dc/elements/1.1/">9781439107973</dc:identifier><dc:title xmlns:dc="http://purl.org/dc/elements/1.1/">Scarlet Nights</dc:title><dc:creator xmlns:dc="http://purl.org/dc/elements/1.1/">Jude Deveraux</dc:creator><dc:publisher xmlns:dc="http://purl.org/dc/elements/1.1/">Simon and Schuster</dc:publisher><dc:description xmlns:dc="http://purl.org/dc/elements/1.1/">&lt;p class="description"&gt;What if you learned that your fiance was not who he claimed to be? Engaged to the charming and seductive Greg Anders, Sara Shaw is happily anticipating her wedding in Edilean, Virginia. The date has been set, the flowers ordered, even her heirloom dress is ready. But just three weeks before the wedding, Greg gets a telephone call during the night and leaves without explanation. Two days later, a man climbs up through a trapdoor in the floor of Sara's apartment, claiming that he is the brother of her best friend and that he's moving in. While Mike Newland is indeed telling the truth about his identity, his reason for being there reaches far deeper. He's an undercover detective, and his assignment is to use Sara to track down a woman who is one of the most notorious criminals in the United Statesand also happens to be the mother of the man Sara plans to marry. Mike thinks the job will be easyif he can figure out how to make a "good" girl like Sara trust him, that is. But Mike has no idea what this mission has in store for him. He's worked hard to keep private his connections to Edilean, which date back to his grandmother's time there in 1941. But as Mike and Sara get to know each other, he can't help but share secrets about himself that he's told no one else. And in return, Sara opens up to Mike about things she could never reveal to Greg. As the pair work together to solve two mysteries, their growing love begins to heal each of them in ways they never could have imagined.&lt;/p&gt;</dc:description></dp:metadata><dp:privateData xmlns:dp="http://ns.adobe.com/digitalpublishing"><totalPageCount xmlns="http://ns.adobe.com/digitaleditions">277</totalPageCount></dp:privateData><dp:tags xmlns:dp="http://ns.adobe.com/digitalpublishing"><dp:tag>private:ub42</dp:tag></dp:tags></contentRecord>